jira_processor/__init__.py
jira_processor/ai_integration.py
jira_processor/jira_interaction.py
jira_processor/processor.py
jira_processor/utils.py
jira_processor-0.1.2.dist-info/LICENSE
jira_processor-0.1.2.dist-info/METADATA
jira_processor-0.1.2.dist-info/WHEEL
jira_processor-0.1.2.dist-info/top_level.txt
jira_processor-0.1.2.dist-info/RECORD
